{
  "id": 182,
  "name": "secretpeguin 4 of 7",
  "slug": "secretpeguin-4-of-7",
  "link": "davenelson/secretpeguin-4-of-7/3646",
  "songs": [
    {
      "url": "4zSmJPG4uTQ"
    },
    {
      "url": "hwnCFJKR2Fo"
    },
    {
      "url": "QVJeQbZgAZ0"
    },
    {
      "url": "9Ib__QLz45I"
    },
    {
      "url": "y-qCuYEUGug"
    },
    {
      "url": "cAZTMDZkPz8"
    },
    {
      "url": "XCdQhhaP_ms"
    },
    {
      "url": "qLrnkK2YEcE"
    },
    {
      "url": "JF2ZgK9JADQ"
    },
    {
      "url": "8IoO5nkxT_4"
    }
  ]
}