{
  "id": 526,
  "name": "suspicious for the winter",
  "slug": "suspicious-for-the-winter",
  "link": "popesaintvictor/suspicious-for-the-winter/266",
  "songs": [
    {
      "url": "7rq16ZX4Vqc"
    },
    {
      "url": "t9DwkpTBof8"
    },
    {
      "url": "uLRnmQ-4Yp0"
    },
    {
      "url": "3LcL7MAqwOc"
    },
    {
      "url": "L-S0qJS9mG4"
    },
    {
      "url": "x0d065IFGP8"
    },
    {
      "url": "8rzME0DSARE"
    },
    {
      "url": "z52wgFDZEIc"
    },
    {
      "url": "mehLx_Fjv_c"
    },
    {
      "url": "4U62lLz19JI"
    },
    {
      "url": "zbnIrnVeNek"
    },
    {
      "url": "sJQk0jDZx8o"
    },
    {
      "url": "yEKbInWml4w"
    },
    {
      "url": "5DUCKGyojpE"
    },
    {
      "url": "uL8ATo1Qpuk"
    },
    {
      "url": "QE7GO79Cxi0"
    },
    {
      "url": "Nv1JLMbq6OQ"
    },
    {
      "url": "1LNgP6-xjdM"
    },
    {
      "url": "6E3znZoFnN8"
    },
    {
      "url": "-Sg7YkPnEYw"
    },
    {
      "url": "kjiXdj21PzA"
    },
    {
      "url": "-UM0RZ3C2oA"
    },
    {
      "url": "CWu4ieBqGFg"
    },
    {
      "url": "ivoYMJq2kiI"
    },
    {
      "url": "zK4WAKc9R4g"
    },
    {
      "url": "So03KFCbc1E"
    },
    {
      "url": "-DSVDcw6iW8"
    },
    {
      "url": "0YuSg4mts9E"
    },
    {
      "url": "jKF5NhoV7hA"
    },
    {
      "url": "qHmSfHY_-Zo"
    },
    {
      "url": "dwNJcaVcjLk"
    },
    {
      "url": "cIQWt3oMids"
    },
    {
      "url": "B-OoisekXIA"
    },
    {
      "url": "0dPS-EHl-FE"
    },
    {
      "url": "0AOVf9p9ht4"
    },
    {
      "url": "8mAzwUFhAFo"
    },
    {
      "url": "xYc_MBjxAL8"
    }
  ]
}