{
  "id": 590,
  "name": "4 8 15 16 23 42",
  "slug": "4-8-15-16-23-42",
  "link": "JeremyMitchell/4_8_15_16_23_42/71",
  "songs": [
    {
      "url": "pG3x22i9oys"
    },
    {
      "url": "lARIX1EMbwA"
    },
    {
      "url": "qeGChOUqQuk"
    },
    {
      "url": "jFg_8u87zT0"
    },
    {
      "url": "jqVrNK4uiB4"
    },
    {
      "url": "eK-7k8MHvnE"
    },
    {
      "url": "1RhriAN7jME"
    },
    {
      "url": "bsRNCvHXHHU"
    },
    {
      "url": "Spvk7tADPaA"
    },
    {
      "url": "-kXhJdecIgc"
    }
  ]
}