{
  "id": 106,
  "name": "elevator love_ 1st floor",
  "slug": "elevator-love-1st-floor",
  "link": "cntndxplsn/elevator-love-1st-floor/4694",
  "songs": [
    {
      "url": "TRVCtbfuDqw"
    },
    {
      "url": "WRKga3eockQ"
    },
    {
      "url": "nFvDz0crnno"
    },
    {
      "url": "QJFCNIzecuU"
    },
    {
      "url": "c9eftz0Hug8"
    },
    {
      "url": "rW5j3z0AMhk"
    },
    {
      "url": "3iOrGK-_1kM"
    },
    {
      "url": "uOTXM5obLcA"
    },
    {
      "url": "dbn3QuBKRDU"
    },
    {
      "url": "UxxajLWwzqY"
    },
    {
      "url": "KtdWGGpvY1s"
    },
    {
      "url": "u06T3ofRpGQ"
    },
    {
      "url": "TKKMfJ8cZoQ"
    },
    {
      "url": "R_2JjIUKEu4"
    },
    {
      "url": "uuZE_IRwLNI"
    }
  ]
}
