{
  "id": 140,
  "name": "the haunting paths",
  "slug": "the-haunting-paths",
  "link": "shoelacegraphic/the-haunting-paths/4146",
  "songs": [
    {
      "url": "xeJ9QNnfGEc"
    },
    {
      "url": "ZzaJhG0u-1g"
    },
    {
      "url": "l7lvWXMcM34"
    },
    {
      "url": "NGNHQKeoSGY"
    },
    {
      "url": "mJxkN9cKQAs"
    },
    {
      "url": "4mjGKqGcn9s"
    },
    {
      "url": "s3e5McLcQoI"
    },
    {
      "url": "5fxykGHHYkM"
    },
    {
      "url": "YzhEc1RvCBE"
    },
    {
      "url": "Qz7JOXTeeBo"
    },
    {
      "url": "WnJz4eUV5qM"
    },
    {
      "url": "6HmMy2ubC7E"
    },
    {
      "url": "DPaK9Ih2jOQ"
    },
    {
      "url": "XgJOAdo8HQQ"
    },
    {
      "url": "F6URtGmqRoo"
    },
    {
      "url": "e4EqjvnWfRM"
    }
  ]
}