{
  "id": 11,
  "name": "process",
  "slug": "process",
  "link": "knockknockfactory/process/5502",
  "songs": [
    {
      "url": "TZkQ65WAa2Q"
    },
    {
      "url": "e6y5nXyiUV0"
    },
    {
      "url": "lMG-iNSM3Mw"
    },
    {
      "url": "L2OSw0m2HbI"
    },
    {
      "url": "TvC5yaSMtP8"
    },
    {
      "url": "2FUD8oHSjiE"
    },
    {
      "url": "hcqB3_MUXlc"
    },
    {
      "url": "bFnA-8H-5lo"
    },
    {
      "url": "yJZ0MIvpfQE"
    },
    {
      "url": "6_UAIUsDYSc"
    }
  ]
}